MANIFEST.in
README.rst
setup.py
grpcrest/__init__.py
grpcrest/grpc_rest.py
grpcrest/utils.py
grpcrest.egg-info/PKG-INFO
grpcrest.egg-info/SOURCES.txt
grpcrest.egg-info/dependency_links.txt
grpcrest.egg-info/entry_points.txt
grpcrest.egg-info/not-zip-safe
grpcrest.egg-info/requires.txt
grpcrest.egg-info/top_level.txt
grpcrest/grpcurl_1.8.7_linux_arm64/LICENSE
grpcrest/grpcurl_1.8.7_linux_arm64/grpcurl
grpcrest/grpcurl_1.8.7_linux_x86_64/LICENSE
grpcrest/grpcurl_1.8.7_linux_x86_64/grpcurl
grpcrest/grpcurl_1.8.7_windows_x86_64/LICENSE
grpcrest/grpcurl_1.8.7_windows_x86_64/grpcurl.exe
grpcrest/images/ServerDetails.png