Metadata-Version: 1.0
Name: grpcrest
Version: 0.17
Summary: REST Wrapper for GRPC
Home-page: http://github.com/storborg/notfound
Author: Dinesh RVL
Author-email: dineshlakshmanan1990@gmail.com
License: MIT
Platform: UNKNOWN
